gensec/__init__.py
gensec/main.py
gensec/commands/__init__.py
gensec/commands/set_dockerfile_template.py
gensec/commands/set_helm_template.py
gensec/commands/templates/python_dockerfile
gensec/commands/templates/helm_template/.helmignore
gensec/commands/templates/helm_template/Chart.yaml
gensec/commands/templates/helm_template/values.yaml
gensec/commands/templates/helm_template/templates/NOTES.txt
gensec/commands/templates/helm_template/templates/_helpers.tpl
gensec/commands/templates/helm_template/templates/deployment.yaml
gensec/commands/templates/helm_template/templates/hpa.yaml
gensec/commands/templates/helm_template/templates/ingress.yaml
gensec/commands/templates/helm_template/templates/service.yaml
gensec/commands/templates/helm_template/templates/serviceaccount.yaml
gensec/commands/templates/helm_template/templates/tests/test-connection.yaml
gensec-0.0.5.dist-info/METADATA
gensec-0.0.5.dist-info/WHEEL
gensec-0.0.5.dist-info/entry_points.txt
gensec-0.0.5.dist-info/top_level.txt
gensec-0.0.5.dist-info/RECORD
