Metadata-Version: 2.1
Name: gensec
Version: 0.0.5
Summary: A Python package for generating secure docker and k8s resources
Home-page: UNKNOWN
License: UNKNOWN
Platform: UNKNOWN
Requires-Dist: click
Requires-Dist: InquirerPy
